spacy_pkuseg-1.0.1.dist-info/METADATA
spacy_pkuseg-1.0.1.dist-info/RECORD
spacy_pkuseg-1.0.1.dist-info/top_level.txt
spacy_pkuseg-1.0.1.dist-info/WHEEL
spacy_pkuseg-1.0.1.dist-info/licenses/LICENSE
spacy_pkuseg/__init__.py
spacy_pkuseg/feature_extractor.pyx
spacy_pkuseg/config.py
spacy_pkuseg/optimizer.py
spacy_pkuseg/data.py
spacy_pkuseg/feature_extractor.cpp
spacy_pkuseg/inference.cpp
spacy_pkuseg/feature_extractor.cpython-310-x86_64-linux-gnu.so
spacy_pkuseg/inference.cpython-310-x86_64-linux-gnu.so
spacy_pkuseg/gradient.py
spacy_pkuseg/inference.pyx
spacy_pkuseg/res_summarize.py
spacy_pkuseg/model.py
spacy_pkuseg/trainer.py
spacy_pkuseg/download.py
spacy_pkuseg/scorer.py
spacy_pkuseg/models/tagIndex.txt
spacy_pkuseg/postag/__init__.py
spacy_pkuseg/postag/feature_extractor.pyx
spacy_pkuseg/postag/feature_extractor.cpp
spacy_pkuseg/postag/feature_extractor.cpython-310-x86_64-linux-gnu.so
spacy_pkuseg/postag/model.py
spacy_pkuseg/dicts/__init__.py
spacy_pkuseg/dicts/default.pkl
spacy_pkuseg/tests/__init__.py
spacy_pkuseg/tests/test_import.py
